odoo8_addon_hr_commission-8.0.1.0.0.99.dev25-py3.8-nspkg.pth
odoo_addons/hr_commission/README.rst
odoo_addons/hr_commission/__init__.py
odoo_addons/hr_commission/__openerp__.py
odoo_addons/hr_commission/i18n/am.po
odoo_addons/hr_commission/i18n/ar.po
odoo_addons/hr_commission/i18n/bg.po
odoo_addons/hr_commission/i18n/bs.po
odoo_addons/hr_commission/i18n/ca.po
odoo_addons/hr_commission/i18n/cs.po
odoo_addons/hr_commission/i18n/da.po
odoo_addons/hr_commission/i18n/de.po
odoo_addons/hr_commission/i18n/el_GR.po
odoo_addons/hr_commission/i18n/en_GB.po
odoo_addons/hr_commission/i18n/es.po
odoo_addons/hr_commission/i18n/es_CR.po
odoo_addons/hr_commission/i18n/es_EC.po
odoo_addons/hr_commission/i18n/es_ES.po
odoo_addons/hr_commission/i18n/es_MX.po
odoo_addons/hr_commission/i18n/es_VE.po
odoo_addons/hr_commission/i18n/et.po
odoo_addons/hr_commission/i18n/eu.po
odoo_addons/hr_commission/i18n/fi.po
odoo_addons/hr_commission/i18n/fr.po
odoo_addons/hr_commission/i18n/fr_CA.po
odoo_addons/hr_commission/i18n/fr_CH.po
odoo_addons/hr_commission/i18n/gl.po
odoo_addons/hr_commission/i18n/hr.po
odoo_addons/hr_commission/i18n/hr_HR.po
odoo_addons/hr_commission/i18n/hr_commission.pot
odoo_addons/hr_commission/i18n/hu.po
odoo_addons/hr_commission/i18n/id.po
odoo_addons/hr_commission/i18n/it.po
odoo_addons/hr_commission/i18n/ja.po
odoo_addons/hr_commission/i18n/lt.po
odoo_addons/hr_commission/i18n/lv.po
odoo_addons/hr_commission/i18n/mk.po
odoo_addons/hr_commission/i18n/mn.po
odoo_addons/hr_commission/i18n/nb.po
odoo_addons/hr_commission/i18n/nb_NO.po
odoo_addons/hr_commission/i18n/nl.po
odoo_addons/hr_commission/i18n/nl_BE.po
odoo_addons/hr_commission/i18n/pl.po
odoo_addons/hr_commission/i18n/pt.po
odoo_addons/hr_commission/i18n/pt_BR.po
odoo_addons/hr_commission/i18n/pt_PT.po
odoo_addons/hr_commission/i18n/ro.po
odoo_addons/hr_commission/i18n/ru.po
odoo_addons/hr_commission/i18n/sk.po
odoo_addons/hr_commission/i18n/sl.po
odoo_addons/hr_commission/i18n/sr@latin.po
odoo8_addon_hr_commission-8.0.1.0.0.99.dev25.dist-info/METADATA
odoo8_addon_hr_commission-8.0.1.0.0.99.dev25.dist-info/WHEEL
odoo8_addon_hr_commission-8.0.1.0.0.99.dev25.dist-info/namespace_packages.txt
odoo8_addon_hr_commission-8.0.1.0.0.99.dev25.dist-info/top_level.txt
odoo8_addon_hr_commission-8.0.1.0.0.99.dev25.dist-info/RECORD
